Metadata-Version: 2.4
Name: llm-tools-docker
Version: 0.1a0
Summary: Run commands in a Docker container via an LLM tool
Author: Simon Willison
License-Expression: Apache-2.0
Project-URL: Homepage, https://github.com/simonw/llm-tools-docker
Project-URL: Changelog, https://github.com/simonw/llm-tools-docker/releases
Project-URL: Issues, https://github.com/simonw/llm-tools-docker/issues
Project-URL: CI, https://github.com/simonw/llm-tools-docker/actions
Requires-Python: >=3.9
License-File: LICENSE
Requires-Dist: llm>=0.26
Provides-Extra: test
Requires-Dist: pytest; extra == "test"
Requires-Dist: llm-echo>=0.3a1; extra == "test"
Dynamic: license-file
